normalize_japanese_addresses/__init__.py
normalize_japanese_addresses/normalize.py
normalize_japanese_addresses/library/__init__.py
normalize_japanese_addresses/library/api.py
normalize_japanese_addresses/library/japaneseNumerics.py
normalize_japanese_addresses/library/patchAddr.py
normalize_japanese_addresses/library/regex.py
normalize_japanese_addresses/library/utils.py
normalize_japanese_addresses-0.0.9.dist-info/LICENSE.txt
normalize_japanese_addresses-0.0.9.dist-info/METADATA
normalize_japanese_addresses-0.0.9.dist-info/WHEEL
normalize_japanese_addresses-0.0.9.dist-info/top_level.txt
normalize_japanese_addresses-0.0.9.dist-info/RECORD
