Metadata-Version: 2.1
Name: normalize-japanese-addresses
Version: 0.0.9
Summary: Ported version of @geolonia/normalize-japanese-addresses
Home-page: https://github.com/Taka710/normalize-japanese-addresses-py
Author: Takahiro Hama
Author-email: taka710.py@gmail.com
Maintainer: Takahiro Hama
Maintainer-email: taka710.py@gmail.com
License: MIT License
Project-URL: Bug Tracker, https://github.com/Taka710/normalize-japanese-addresses-py/issues
Platform: UNKNOWN
Classifier: Programming Language :: Python :: 3
Classifier: Programming Language :: Python :: 3.8
Classifier: License :: OSI Approved :: MIT License
Requires-Python: >=3.8
